apollo_torch/__init__.py
apollo_torch/adafactor.py
apollo_torch/adamw.py
apollo_torch/adamw8bit.py
apollo_torch/apollo.py
apollo_torch/q_apollo.py
apollo_torch/random_projector.py
apollo_torch/svd_projector.py
apollo_torch-1.0.3.dist-info/LICENSE
apollo_torch-1.0.3.dist-info/METADATA
apollo_torch-1.0.3.dist-info/WHEEL
apollo_torch-1.0.3.dist-info/top_level.txt
apollo_torch-1.0.3.dist-info/RECORD
