Metadata-Version: 2.2
Name: apollo-torch
Version: 1.0.3
Summary: APOLLO: SGD-like Memory, AdamW-level Performance
Home-page: https://github.com/zhuhanqing/APOLLO
Author: Hanqing Zhu
Author-email: hqzhu@utexas.edu
License: CC-BY-NC
Classifier: Programming Language :: Python :: 3
Classifier: License :: Other/Proprietary License
Classifier: Operating System :: OS Independent
Requires-Python: >=3.7
License-File: LICENSE
Requires-Dist: torch
Requires-Dist: transformers
Requires-Dist: bitsandbytes
Dynamic: author
Dynamic: author-email
Dynamic: classifier
Dynamic: description
Dynamic: description-content-type
Dynamic: home-page
Dynamic: license
Dynamic: requires-dist
Dynamic: requires-python
Dynamic: summary
